README
setup.py
alt/__init__.py
alt/common.py
alt/config.py
alt/http.py
alt/runner.py
alt/skeleton.py
alt/tests.py
alt.egg-info/PKG-INFO
alt.egg-info/SOURCES.txt
alt.egg-info/dependency_links.txt
alt.egg-info/not-zip-safe
alt.egg-info/requires.txt
alt.egg-info/top_level.txt
alt/skeleton/secrets.yaml
alt/skeleton/testRunner.py
alt/skeleton/test_code.py
alt/skeleton/tests.yaml