Metadata-Version: 1.0
Name: alt
Version: 0.0.3
Summary: Web API level tests and test runner
Home-page: https://github.com/kevwo/alt
Author: Kevin Woodmansee
Author-email: kevinwoodmansee@gmail.com
License: MIT
Platform: UNKNOWN
